pydantic2md/__init__.py
pydantic2md/core.py
pydantic2md-0.1.0.dist-info/LICENSE
pydantic2md-0.1.0.dist-info/METADATA
pydantic2md-0.1.0.dist-info/WHEEL
pydantic2md-0.1.0.dist-info/RECORD
