Metadata-Version: 2.1
Name: pydantic2md
Version: 0.1.0
Summary: Pydantic to Markdown converter.
License: Apache V2
Author: Dref360
Author-email: frederic.branchaud.charron@gmail.com
Requires-Python: >=3.9,<4.0
Classifier: License :: Other/Proprietary License
Classifier: Programming Language :: Python :: 3
Classifier: Programming Language :: Python :: 3.9
Classifier: Programming Language :: Python :: 3.10
Classifier: Programming Language :: Python :: 3.11
Requires-Dist: pydantic (>=2.6.4,<3.0.0)
